[
  {
    "fullName": "Arthur Miller",
    "givenNames": [
      "Arthur",
      "Asher"
    ],
    "familyName": "Miller",
    "wikipedia": "https://en.wikipedia.org/wiki/Arthur_Miller",
    "occupation": "Playwright, essayist",
    "achievements": [
      "Pulitzer Prize for Drama (The Crucible)",
      "Tony Award for Best Play (Death of a Salesman)"
    ],
    "yearBorn": 1915,
    "yearDied": 2005
  },
  {
    "fullName": "George Miller",
    "givenNames": [
      "George"
    ],
    "familyName": "Miller",
    "wikipedia": "https://en.wikipedia.org/wiki/George_Miller_(filmmaker)",
    "occupation": "Film director, screenwriter, producer",
    "achievements": [
      "Academy Award for Best Original Screenplay (Mad Max: Fury Road)"
    ],
    "yearBorn": 1945
  },
  {
    "fullName": "Glenn Miller",
    "givenNames": [
      "Glenn",
      "Alton"
    ],
    "familyName": "Miller",
    "wikipedia": "https://en.wikipedia.org/wiki/Glenn_Miller",
    "occupation": "Big Band Musician, Composer, Arranger",
    "achievements": [
      "Led one of the most popular big bands in history",
      "Wrote classic songs like 'In the Mood' and 'Moonlight Serenade'"
    ],
    "yearBorn": 1904,
    "yearDied": 1944
  }
]