[
  {
    "fullName": "Charlie Bird",
    "givenNames": [
      "Charles",
      "Brown"
    ],
    "familyName": "Bird",
    "wikipedia": "https://en.wikipedia.org/wiki/Charlie_Bird",
    "occupation": "Irish broadcaster and journalist",
    "achievements": [
      "Long career with RTÉ as a reporter and presenter.",
      "Known for his coverage of major events in Ireland and abroad."
    ],
    "yearBorn": 1949
  },
  {
    "fullName": "Andrew Bird",
    "givenNames": [
      "Andrew",
      "Wegman"
    ],
    "familyName": "Bird",
    "wikipedia": "https://en.wikipedia.org/wiki/Andrew_Bird",
    "occupation": "American multi-instrumentalist, singer-songwriter and whistler",
    "achievements": [
      "Known for his distinctive whistling style.",
      "Released critically acclaimed albums like 'Armchair Apocrypha' and 'Noble Beast'.",
      "Collaborated with various artists including Fiona Apple and the Decemberists."
    ],
    "yearBorn": 1973
  },
  {
    "fullName": "John Bird",
    "givenNames": [
      "John",
      "Michael"
    ],
    "familyName": "Bird",
    "wikipedia": "https://en.wikipedia.org/wiki/John_Bird_(actor)",
    "occupation": "British actor and comedian",
    "achievements": [
      "Known for his roles in Monty Python's Flying Circus and other comedy productions"
    ],
    "yearBorn": 1937
  }
]