[
  {
    "fullName": "Robert Chambers",
    "givenNames": [
      "Robert"
    ],
    "familyName": "Chambers",
    "wikipedia": "https://en.wikipedia.org/wiki/Robert_Chambers_(publisher,_born_1802)",
    "occupation": "Writer, Editor",
    "achievements": [
      "Authored the influential and controversial Victorian-era novel 'The Book of Days'",
      "Contributed significantly to the development of encyclopedias and dictionaries in the 19th century"
    ],
    "yearBorn": 1802,
    "yearDied": 1871
  },
  {
    "fullName": "Emma Chambers",
    "givenNames": [
      "Emma",
      "Gwynedd",
      "Mary"
    ],
    "familyName": "Chambers",
    "wikipedia": "https://en.wikipedia.org/wiki/Emma_Chambers",
    "occupation": "Actress",
    "achievements": [
      "Known for her roles in British comedy series such as 'The Vicar of Dibley'",
      "Won critical acclaim and audience adoration for her comedic timing and memorable characters"
    ],
    "yearBorn": 1964,
    "yearDied": 2018
  }
]