[
  {
    "fullName": "Barry Cunliffe",
    "givenNames": [
      "Barrington",
      "Windsor",
      "Barry"
    ],
    "familyName": "Cunliffe",
    "wikipedia": "https://en.wikipedia.org/wiki/Barry_Cunliffe",
    "occupation": "Archaeologist",
    "achievements": [
      "Emeritus Professor of Archaeology at the University of Oxford",
      "Known for his work on Roman Britain and Iron Age Europe",
      "Author of numerous books and articles on archaeology"
    ],
    "yearBorn": 1936
  },
  {
    "fullName": "John Cunliffe",
    "givenNames": [
      "John",
      "Arthur"
    ],
    "familyName": "Cunliffe",
    "wikipedia": "https://en.wikipedia.org/wiki/John_Cunliffe_(author)",
    "occupation": "Children's author and screenwriter",
    "achievements": [
      "Creator of the popular children's television series Postman Pat",
      "Author of numerous books for children"
    ],
    "yearBorn": 1933,
    "yearDied": 2018
  }
]