[
  {
    "fullName": "Akshay Kumar",
    "givenNames": [
      "Akshay"
    ],
    "familyName": "Kumar",
    "wikipedia": "https://en.wikipedia.org/wiki/Akshay_Kumar",
    "occupation": "Actor, Producer",
    "achievements": [
      "One of the highest-paid actors in Bollywood.",
      "Known for his action and comedy roles."
    ],
    "yearBorn": 1967
  },
  {
    "fullName": "Manoj Kumar",
    "givenNames": [
      "Manoj"
    ],
    "familyName": "Kumar",
    "wikipedia": "https://en.wikipedia.org/wiki/Manoj_Kumar",
    "occupation": "Actor, Director, Producer",
    "achievements": [
      "Known as 'Bharat Kumar' for his patriotic films.",
      "Recipient of the Padma Shri award."
    ],
    "yearBorn": 1937
  }
]